fluffyclone/__init__.py
fluffyclone/compiled.py
fluffyclone/distribution.py
fluffyclone/model.py
fluffyclone/sampling.py
fluffyclone/utils.py
fluffyclone-0.1.3.dist-info/METADATA
fluffyclone-0.1.3.dist-info/WHEEL
fluffyclone-0.1.3.dist-info/licenses/LICENSE.txt
fluffyclone-0.1.3.dist-info/RECORD
